[{"text": "febayk46-3", "expandable": 1, "leaf": 0, "id": "ebayk.servers.*.febayk46-3", "allowChildren": 1}, {"text": "febayk46-4", "expandable": 1, "leaf": 0, "id": "ebayk.servers.*.febayk46-4", "allowChildren": 1}, {"text": "febayk47-3", "expandable": 1, "leaf": 0, "id": "ebayk.servers.*.febayk47-3", "allowChildren": 1}, {"text": "febayk47-4", "expandable": 1, "leaf": 0, "id": "ebayk.servers.*.febayk47-4", "allowChildren": 1}, {"text": "fkapi46-1", "expandable": 1, "leaf": 0, "id": "ebayk.servers.*.fkapi46-1", "allowChildren": 1}, {"text": "fkapi46-2", "expandable": 1, "leaf": 0, "id": "ebayk.servers.*.fkapi46-2", "allowChildren": 1}, {"text": "fkapi46-3", "expandable": 1, "leaf": 0, "id": "ebayk.servers.*.fkapi46-3", "allowChildren": 1}, {"text": "fkapi46-4", "expandable": 1, "leaf": 0, "id": "ebayk.servers.*.fkapi46-4", "allowChildren": 1}, {"text": "fkapi47-1", "expandable": 1, "leaf": 0, "id": "ebayk.servers.*.fkapi47-1", "allowChildren": 1}, {"text": "fkapi47-2", "expandable": 1, "leaf": 0, "id": "ebayk.servers.*.fkapi47-2", "allowChildren": 1}, {"text": "fkapi47-3", "expandable": 1, "leaf": 0, "id": "ebayk.servers.*.fkapi47-3", "allowChildren": 1}, {"text": "fkapi47-4", "expandable": 1, "leaf": 0, "id": "ebayk.servers.*.fkapi47-4", "allowChildren": 1}, {"text": "fkcs38-1", "expandable": 1, "leaf": 0, "id": "ebayk.servers.*.fkcs38-1", "allowChildren": 1}, {"text": "fkcs38-2", "expandable": 1, "leaf": 0, "id": "ebayk.servers.*.fkcs38-2", "allowChildren": 1}, {"text": "kapi46-1", "expandable": 1, "leaf": 0, "id": "ebayk.servers.*.kapi46-1", "allowChildren": 1}, {"text": "kapi46-2", "expandable": 1, "leaf": 0, "id": "ebayk.servers.*.kapi46-2", "allowChildren": 1}, {"text": "kapi46-3", "expandable": 1, "leaf": 0, "id": "ebayk.servers.*.kapi46-3", "allowChildren": 1}, {"text": "kapi46-4", "expandable": 1, "leaf": 0, "id": "ebayk.servers.*.kapi46-4", "allowChildren": 1}, {"text": "kapi47-1", "expandable": 1, "leaf": 0, "id": "ebayk.servers.*.kapi47-1", "allowChildren": 1}, {"text": "kapi47-100", "expandable": 1, "leaf": 0, "id": "ebayk.servers.*.kapi47-100", "allowChildren": 1}, {"text": "kapi47-2", "expandable": 1, "leaf": 0, "id": "ebayk.servers.*.kapi47-2", "allowChildren": 1}, {"text": "kapi47-3", "expandable": 1, "leaf": 0, "id": "ebayk.servers.*.kapi47-3", "allowChildren": 1}, {"text": "kapi47-4", "expandable": 1, "leaf": 0, "id": "ebayk.servers.*.kapi47-4", "allowChildren": 1}, {"text": "kappmon38-1", "expandable": 1, "leaf": 0, "id": "ebayk.servers.*.kappmon38-1", "allowChildren": 1}, {"text": "kbatchdb46-1", "expandable": 1, "leaf": 0, "id": "ebayk.servers.*.kbatchdb46-1", "allowChildren": 1}, {"text": "kbatchdb46-2", "expandable": 1, "leaf": 0, "id": "ebayk.servers.*.kbatchdb46-2", "allowChildren": 1}, {"text": "kbatchdb47-1", "expandable": 1, "leaf": 0, "id": "ebayk.servers.*.kbatchdb47-1", "allowChildren": 1}, {"text": "kbatchdb47-2", "expandable": 1, "leaf": 0, "id": "ebayk.servers.*.kbatchdb47-2", "allowChildren": 1}, {"text": "kcron46-1", "expandable": 1, "leaf": 0, "id": "ebayk.servers.*.kcron46-1", "allowChildren": 1}, {"text": "kcron47-1", "expandable": 1, "leaf": 0, "id": "ebayk.servers.*.kcron47-1", "allowChildren": 1}, {"text": "kcs38-1", "expandable": 1, "leaf": 0, "id": "ebayk.servers.*.kcs38-1", "allowChildren": 1}, {"text": "kcs38-2", "expandable": 1, "leaf": 0, "id": "ebayk.servers.*.kcs38-2", "allowChildren": 1}, {"text": "kdashboard46-1", "expandable": 1, "leaf": 0, "id": "ebayk.servers.*.kdashboard46-1", "allowChildren": 1}, {"text": "kdb46-1", "expandable": 1, "leaf": 0, "id": "ebayk.servers.*.kdb46-1", "allowChildren": 1}, {"text": "kdb46-2", "expandable": 1, "leaf": 0, "id": "ebayk.servers.*.kdb46-2", "allowChildren": 1}, {"text": "kdb46-3", "expandable": 1, "leaf": 0, "id": "ebayk.servers.*.kdb46-3", "allowChildren": 1}, {"text": "kdb46-4", "expandable": 1, "leaf": 0, "id": "ebayk.servers.*.kdb46-4", "allowChildren": 1}, {"text": "kdb46-5", "expandable": 1, "leaf": 0, "id": "ebayk.servers.*.kdb46-5", "allowChildren": 1}, {"text": "kdb47-1", "expandable": 1, "leaf": 0, "id": "ebayk.servers.*.kdb47-1", "allowChildren": 1}, {"text": "kdb47-2", "expandable": 1, "leaf": 0, "id": "ebayk.servers.*.kdb47-2", "allowChildren": 1}, {"text": "kdblag46-1", "expandable": 1, "leaf": 0, "id": "ebayk.servers.*.kdblag46-1", "allowChildren": 1}, {"text": "kdblag47-1", "expandable": 1, "leaf": 0, "id": "ebayk.servers.*.kdblag47-1", "allowChildren": 1}, {"text": "kdbmaster46-1", "expandable": 1, "leaf": 0, "id": "ebayk.servers.*.kdbmaster46-1", "allowChildren": 1}, {"text": "kdbmaster46-2", "expandable": 1, "leaf": 0, "id": "ebayk.servers.*.kdbmaster46-2", "allowChildren": 1}, {"text": "kdbmaster47-1", "expandable": 1, "leaf": 0, "id": "ebayk.servers.*.kdbmaster47-1", "allowChildren": 1}, {"text": "kdbmaster47-2", "expandable": 1, "leaf": 0, "id": "ebayk.servers.*.kdbmaster47-2", "allowChildren": 1}, {"text": "kdwh38-1", "expandable": 1, "leaf": 0, "id": "ebayk.servers.*.kdwh38-1", "allowChildren": 1}, {"text": "kgraylog47-1", "expandable": 1, "leaf": 0, "id": "ebayk.servers.*.kgraylog47-1", "allowChildren": 1}, {"text": "khelpcenter46-1", "expandable": 1, "leaf": 0, "id": "ebayk.servers.*.khelpcenter46-1", "allowChildren": 1}, {"text": "khelpcenter46-2", "expandable": 1, "leaf": 0, "id": "ebayk.servers.*.khelpcenter46-2", "allowChildren": 1}, {"text": "khelpcenter47-1", "expandable": 1, "leaf": 0, "id": "ebayk.servers.*.khelpcenter47-1", "allowChildren": 1}, {"text": "khelpcenter47-2", "expandable": 1, "leaf": 0, "id": "ebayk.servers.*.khelpcenter47-2", "allowChildren": 1}, {"text": "klogstash46-1", "expandable": 1, "leaf": 0, "id": "ebayk.servers.*.klogstash46-1", "allowChildren": 1}, {"text": "klogstash47-1", "expandable": 1, "leaf": 0, "id": "ebayk.servers.*.klogstash47-1", "allowChildren": 1}, {"text": "kmemsession46-1", "expandable": 1, "leaf": 0, "id": "ebayk.servers.*.kmemsession46-1", "allowChildren": 1}, {"text": "kmemsession46-2", "expandable": 1, "leaf": 0, "id": "ebayk.servers.*.kmemsession46-2", "allowChildren": 1}, {"text": "kmemsession47-1", "expandable": 1, "leaf": 0, "id": "ebayk.servers.*.kmemsession47-1", "allowChildren": 1}, {"text": "kmemsession47-2", "expandable": 1, "leaf": 0, "id": "ebayk.servers.*.kmemsession47-2", "allowChildren": 1}, {"text": "kmobile46-1", "expandable": 1, "leaf": 0, "id": "ebayk.servers.*.kmobile46-1", "allowChildren": 1}, {"text": "kmobile46-2", "expandable": 1, "leaf": 0, "id": "ebayk.servers.*.kmobile46-2", "allowChildren": 1}, {"text": "kmobile47-1", "expandable": 1, "leaf": 0, "id": "ebayk.servers.*.kmobile47-1", "allowChildren": 1}, {"text": "kmobile47-2", "expandable": 1, "leaf": 0, "id": "ebayk.servers.*.kmobile47-2", "allowChildren": 1}, {"text": "kmobilepush46-1", "expandable": 1, "leaf": 0, "id": "ebayk.servers.*.kmobilepush46-1", "allowChildren": 1}, {"text": "kmobilepush46-2", "expandable": 1, "leaf": 0, "id": "ebayk.servers.*.kmobilepush46-2", "allowChildren": 1}, {"text": "kmobilepush47-1", "expandable": 1, "leaf": 0, "id": "ebayk.servers.*.kmobilepush47-1", "allowChildren": 1}, {"text": "kmobilepush47-2", "expandable": 1, "leaf": 0, "id": "ebayk.servers.*.kmobilepush47-2", "allowChildren": 1}, {"text": "kmongo46-1", "expandable": 1, "leaf": 0, "id": "ebayk.servers.*.kmongo46-1", "allowChildren": 1}, {"text": "kmongo46-2", "expandable": 1, "leaf": 0, "id": "ebayk.servers.*.kmongo46-2", "allowChildren": 1}, {"text": "kmongo47-1", "expandable": 1, "leaf": 0, "id": "ebayk.servers.*.kmongo47-1", "allowChildren": 1}, {"text": "kmongo47-2", "expandable": 1, "leaf": 0, "id": "ebayk.servers.*.kmongo47-2", "allowChildren": 1}, {"text": "koeb46-1", "expandable": 1, "leaf": 0, "id": "ebayk.servers.*.koeb46-1", "allowChildren": 1}, {"text": "koeb46-2", "expandable": 1, "leaf": 0, "id": "ebayk.servers.*.koeb46-2", "allowChildren": 1}, {"text": "koeb46-3", "expandable": 1, "leaf": 0, "id": "ebayk.servers.*.koeb46-3", "allowChildren": 1}, {"text": "koeb47-1", "expandable": 1, "leaf": 0, "id": "ebayk.servers.*.koeb47-1", "allowChildren": 1}, {"text": "koeb47-2", "expandable": 1, "leaf": 0, "id": "ebayk.servers.*.koeb47-2", "allowChildren": 1}, {"text": "koeb47-3", "expandable": 1, "leaf": 0, "id": "ebayk.servers.*.koeb47-3", "allowChildren": 1}, {"text": "koebrt46-1", "expandable": 1, "leaf": 0, "id": "ebayk.servers.*.koebrt46-1", "allowChildren": 1}, {"text": "koebrt46-2", "expandable": 1, "leaf": 0, "id": "ebayk.servers.*.koebrt46-2", "allowChildren": 1}, {"text": "koebrt47-1", "expandable": 1, "leaf": 0, "id": "ebayk.servers.*.koebrt47-1", "allowChildren": 1}, {"text": "koebrt47-2", "expandable": 1, "leaf": 0, "id": "ebayk.servers.*.koebrt47-2", "allowChildren": 1}, {"text": "kpdf46-2", "expandable": 1, "leaf": 0, "id": "ebayk.servers.*.kpdf46-2", "allowChildren": 1}, {"text": "kpdf47-1", "expandable": 1, "leaf": 0, "id": "ebayk.servers.*.kpdf47-1", "allowChildren": 1}, {"text": "kreplyts46-1", "expandable": 1, "leaf": 0, "id": "ebayk.servers.*.kreplyts46-1", "allowChildren": 1}, {"text": "kreplyts46-2", "expandable": 1, "leaf": 0, "id": "ebayk.servers.*.kreplyts46-2", "allowChildren": 1}, {"text": "kreplyts47-1", "expandable": 1, "leaf": 0, "id": "ebayk.servers.*.kreplyts47-1", "allowChildren": 1}, {"text": "kreplyts47-2", "expandable": 1, "leaf": 0, "id": "ebayk.servers.*.kreplyts47-2", "allowChildren": 1}, {"text": "kreplytsmb46-1", "expandable": 1, "leaf": 0, "id": "ebayk.servers.*.kreplytsmb46-1", "allowChildren": 1}, {"text": "kreplytsmb46-2", "expandable": 1, "leaf": 0, "id": "ebayk.servers.*.kreplytsmb46-2", "allowChildren": 1}, {"text": "kreplytsmb47-1", "expandable": 1, "leaf": 0, "id": "ebayk.servers.*.kreplytsmb47-1", "allowChildren": 1}, {"text": "kreplytsmb47-2", "expandable": 1, "leaf": 0, "id": "ebayk.servers.*.kreplytsmb47-2", "allowChildren": 1}, {"text": "kreplytssearch46-1", "expandable": 1, "leaf": 0, "id": "ebayk.servers.*.kreplytssearch46-1", "allowChildren": 1}, {"text": "kreplytssearch46-2", "expandable": 1, "leaf": 0, "id": "ebayk.servers.*.kreplytssearch46-2", "allowChildren": 1}, {"text": "kreplytssearch46-3", "expandable": 1, "leaf": 0, "id": "ebayk.servers.*.kreplytssearch46-3", "allowChildren": 1}, {"text": "kreplytssearch46-4", "expandable": 1, "leaf": 0, "id": "ebayk.servers.*.kreplytssearch46-4", "allowChildren": 1}, {"text": "kreplytssearch46-5", "expandable": 1, "leaf": 0, "id": "ebayk.servers.*.kreplytssearch46-5", "allowChildren": 1}, {"text": "kreplytssearch47-1", "expandable": 1, "leaf": 0, "id": "ebayk.servers.*.kreplytssearch47-1", "allowChildren": 1}, {"text": "kreplytssearch47-2", "expandable": 1, "leaf": 0, "id": "ebayk.servers.*.kreplytssearch47-2", "allowChildren": 1}, {"text": "kreplytssearch47-3", "expandable": 1, "leaf": 0, "id": "ebayk.servers.*.kreplytssearch47-3", "allowChildren": 1}, {"text": "kreplytssearch47-4", "expandable": 1, "leaf": 0, "id": "ebayk.servers.*.kreplytssearch47-4", "allowChildren": 1}, {"text": "kreplytssearch47-5", "expandable": 1, "leaf": 0, "id": "ebayk.servers.*.kreplytssearch47-5", "allowChildren": 1}, {"text": "kreplytssearchmaster46-1", "expandable": 1, "leaf": 0, "id": "ebayk.servers.*.kreplytssearchmaster46-1", "allowChildren": 1}, {"text": "kreplytssearchmaster46-2", "expandable": 1, "leaf": 0, "id": "ebayk.servers.*.kreplytssearchmaster46-2", "allowChildren": 1}, {"text": "kreplytssearchmaster47-1", "expandable": 1, "leaf": 0, "id": "ebayk.servers.*.kreplytssearchmaster47-1", "allowChildren": 1}, {"text": "kreplytssearchmaster47-2", "expandable": 1, "leaf": 0, "id": "ebayk.servers.*.kreplytssearchmaster47-2", "allowChildren": 1}, {"text": "kriak46-1", "expandable": 1, "leaf": 0, "id": "ebayk.servers.*.kriak46-1", "allowChildren": 1}, {"text": "kriak46-2", "expandable": 1, "leaf": 0, "id": "ebayk.servers.*.kriak46-2", "allowChildren": 1}, {"text": "kriak46-3", "expandable": 1, "leaf": 0, "id": "ebayk.servers.*.kriak46-3", "allowChildren": 1}, {"text": "kriak46-4", "expandable": 1, "leaf": 0, "id": "ebayk.servers.*.kriak46-4", "allowChildren": 1}, {"text": "kriak46-5", "expandable": 1, "leaf": 0, "id": "ebayk.servers.*.kriak46-5", "allowChildren": 1}, {"text": "kriak46-6", "expandable": 1, "leaf": 0, "id": "ebayk.servers.*.kriak46-6", "allowChildren": 1}, {"text": "kriak47-1", "expandable": 1, "leaf": 0, "id": "ebayk.servers.*.kriak47-1", "allowChildren": 1}, {"text": "kriak47-2", "expandable": 1, "leaf": 0, "id": "ebayk.servers.*.kriak47-2", "allowChildren": 1}, {"text": "kriak47-3", "expandable": 1, "leaf": 0, "id": "ebayk.servers.*.kriak47-3", "allowChildren": 1}, {"text": "kriak47-4", "expandable": 1, "leaf": 0, "id": "ebayk.servers.*.kriak47-4", "allowChildren": 1}, {"text": "kriak47-5", "expandable": 1, "leaf": 0, "id": "ebayk.servers.*.kriak47-5", "allowChildren": 1}, {"text": "kriak47-6", "expandable": 1, "leaf": 0, "id": "ebayk.servers.*.kriak47-6", "allowChildren": 1}, {"text": "ksolr46-1", "expandable": 1, "leaf": 0, "id": "ebayk.servers.*.ksolr46-1", "allowChildren": 1}, {"text": "ksolr46-10", "expandable": 1, "leaf": 0, "id": "ebayk.servers.*.ksolr46-10", "allowChildren": 1}, {"text": "ksolr46-11", "expandable": 1, "leaf": 0, "id": "ebayk.servers.*.ksolr46-11", "allowChildren": 1}, {"text": "ksolr46-2", "expandable": 1, "leaf": 0, "id": "ebayk.servers.*.ksolr46-2", "allowChildren": 1}, {"text": "ksolr46-3", "expandable": 1, "leaf": 0, "id": "ebayk.servers.*.ksolr46-3", "allowChildren": 1}, {"text": "ksolr46-4", "expandable": 1, "leaf": 0, "id": "ebayk.servers.*.ksolr46-4", "allowChildren": 1}, {"text": "ksolr46-5", "expandable": 1, "leaf": 0, "id": "ebayk.servers.*.ksolr46-5", "allowChildren": 1}, {"text": "ksolr46-6", "expandable": 1, "leaf": 0, "id": "ebayk.servers.*.ksolr46-6", "allowChildren": 1}, {"text": "ksolr46-7", "expandable": 1, "leaf": 0, "id": "ebayk.servers.*.ksolr46-7", "allowChildren": 1}, {"text": "ksolr46-8", "expandable": 1, "leaf": 0, "id": "ebayk.servers.*.ksolr46-8", "allowChildren": 1}, {"text": "ksolr46-9", "expandable": 1, "leaf": 0, "id": "ebayk.servers.*.ksolr46-9", "allowChildren": 1}, {"text": "ksolr47-1", "expandable": 1, "leaf": 0, "id": "ebayk.servers.*.ksolr47-1", "allowChildren": 1}, {"text": "ksolr47-10", "expandable": 1, "leaf": 0, "id": "ebayk.servers.*.ksolr47-10", "allowChildren": 1}, {"text": "ksolr47-11", "expandable": 1, "leaf": 0, "id": "ebayk.servers.*.ksolr47-11", "allowChildren": 1}, {"text": "ksolr47-2", "expandable": 1, "leaf": 0, "id": "ebayk.servers.*.ksolr47-2", "allowChildren": 1}, {"text": "ksolr47-3", "expandable": 1, "leaf": 0, "id": "ebayk.servers.*.ksolr47-3", "allowChildren": 1}, {"text": "ksolr47-4", "expandable": 1, "leaf": 0, "id": "ebayk.servers.*.ksolr47-4", "allowChildren": 1}, {"text": "ksolr47-5", "expandable": 1, "leaf": 0, "id": "ebayk.servers.*.ksolr47-5", "allowChildren": 1}, {"text": "ksolr47-6", "expandable": 1, "leaf": 0, "id": "ebayk.servers.*.ksolr47-6", "allowChildren": 1}, {"text": "ksolr47-7", "expandable": 1, "leaf": 0, "id": "ebayk.servers.*.ksolr47-7", "allowChildren": 1}, {"text": "ksolr47-8", "expandable": 1, "leaf": 0, "id": "ebayk.servers.*.ksolr47-8", "allowChildren": 1}, {"text": "ksolr47-9", "expandable": 1, "leaf": 0, "id": "ebayk.servers.*.ksolr47-9", "allowChildren": 1}, {"text": "ksolrallads46-1", "expandable": 1, "leaf": 0, "id": "ebayk.servers.*.ksolrallads46-1", "allowChildren": 1}, {"text": "ksolrallads46-2", "expandable": 1, "leaf": 0, "id": "ebayk.servers.*.ksolrallads46-2", "allowChildren": 1}, {"text": "ksolrallads47-1", "expandable": 1, "leaf": 0, "id": "ebayk.servers.*.ksolrallads47-1", "allowChildren": 1}, {"text": "ksolrallads47-2", "expandable": 1, "leaf": 0, "id": "ebayk.servers.*.ksolrallads47-2", "allowChildren": 1}, {"text": "ksolras46-1", "expandable": 1, "leaf": 0, "id": "ebayk.servers.*.ksolras46-1", "allowChildren": 1}, {"text": "ksolras46-2", "expandable": 1, "leaf": 0, "id": "ebayk.servers.*.ksolras46-2", "allowChildren": 1}, {"text": "ksolras47-1", "expandable": 1, "leaf": 0, "id": "ebayk.servers.*.ksolras47-1", "allowChildren": 1}, {"text": "ksolras47-2", "expandable": 1, "leaf": 0, "id": "ebayk.servers.*.ksolras47-2", "allowChildren": 1}, {"text": "ksolrmaster46-1", "expandable": 1, "leaf": 0, "id": "ebayk.servers.*.ksolrmaster46-1", "allowChildren": 1}, {"text": "ksolrmaster47-1", "expandable": 1, "leaf": 0, "id": "ebayk.servers.*.ksolrmaster47-1", "allowChildren": 1}, {"text": "ksolrtns46-1", "expandable": 1, "leaf": 0, "id": "ebayk.servers.*.ksolrtns46-1", "allowChildren": 1}, {"text": "ksolrtns46-2", "expandable": 1, "leaf": 0, "id": "ebayk.servers.*.ksolrtns46-2", "allowChildren": 1}, {"text": "ksolrvarnish46-1", "expandable": 1, "leaf": 0, "id": "ebayk.servers.*.ksolrvarnish46-1", "allowChildren": 1}, {"text": "ksolrvarnish46-2", "expandable": 1, "leaf": 0, "id": "ebayk.servers.*.ksolrvarnish46-2", "allowChildren": 1}, {"text": "ksolrvarnish47-1", "expandable": 1, "leaf": 0, "id": "ebayk.servers.*.ksolrvarnish47-1", "allowChildren": 1}, {"text": "ksolrvarnish47-2", "expandable": 1, "leaf": 0, "id": "ebayk.servers.*.ksolrvarnish47-2", "allowChildren": 1}, {"text": "ktableaudb38-1", "expandable": 1, "leaf": 0, "id": "ebayk.servers.*.ktableaudb38-1", "allowChildren": 1}, {"text": "ktns46-1", "expandable": 1, "leaf": 0, "id": "ebayk.servers.*.ktns46-1", "allowChildren": 1}, {"text": "ktns47-1", "expandable": 1, "leaf": 0, "id": "ebayk.servers.*.ktns47-1", "allowChildren": 1}, {"text": "kvarnish46-1", "expandable": 1, "leaf": 0, "id": "ebayk.servers.*.kvarnish46-1", "allowChildren": 1}, {"text": "kvarnish46-2", "expandable": 1, "leaf": 0, "id": "ebayk.servers.*.kvarnish46-2", "allowChildren": 1}, {"text": "kvarnish47-1", "expandable": 1, "leaf": 0, "id": "ebayk.servers.*.kvarnish47-1", "allowChildren": 1}, {"text": "kvarnish47-2", "expandable": 1, "leaf": 0, "id": "ebayk.servers.*.kvarnish47-2", "allowChildren": 1}]